README.md
setup.py
quivr_core/__init__.py
quivr_core/base_config.py
quivr_core/config.py
quivr_core/brain/__init__.py
quivr_core/brain/brain.py
quivr_core/brain/brain_defaults.py
quivr_core/brain/info.py
quivr_core/brain/serialization.py
quivr_core/files/__init__.py
quivr_core/files/file.py
quivr_core/llm/__init__.py
quivr_core/llm/llm_endpoint.py
quivr_core/llm_tools/__init__.py
quivr_core/llm_tools/entity.py
quivr_core/llm_tools/llm_tools.py
quivr_core/llm_tools/other_tools.py
quivr_core/llm_tools/web_search_tools.py
quivr_core/processor/__init__.py
quivr_core/processor/processor_base.py
quivr_core/processor/registry.py
quivr_core/processor/splitter.py
quivr_core/processor/implementations/__init__.py
quivr_core/processor/implementations/default.py
quivr_core/processor/implementations/megaparse_processor.py
quivr_core/processor/implementations/simple_txt_processor.py
quivr_core/processor/implementations/tika_processor.py
quivr_core/rag/__init__.py
quivr_core/rag/prompts.py
quivr_core/rag/quivr_rag.py
quivr_core/rag/quivr_rag_langgraph.py
quivr_core/rag/utils.py
quivr_core/rag/entities/__init__.py
quivr_core/rag/entities/chat.py
quivr_core/rag/entities/config.py
quivr_core/rag/entities/models.py
quivr_core/storage/__init__.py
quivr_core/storage/file.py
quivr_core/storage/local_storage.py
quivr_core/storage/storage_base.py
quivr_modified_milvus.egg-info/PKG-INFO
quivr_modified_milvus.egg-info/SOURCES.txt
quivr_modified_milvus.egg-info/dependency_links.txt
quivr_modified_milvus.egg-info/requires.txt
quivr_modified_milvus.egg-info/top_level.txt
tests/__init__.py
tests/conftest.py
tests/fixture_chunks.py
tests/test_brain.py
tests/test_chat_history.py
tests/test_config.py
tests/test_llm_endpoint.py
tests/test_quivr_file.py
tests/test_quivr_rag.py
tests/test_utils.py
tests/processor/__init__.py
tests/processor/test_default_implementations.py
tests/processor/test_registry.py
tests/processor/test_simple_txt_processor.py
tests/processor/test_tika_processor.py
tests/processor/test_txt_processor.py
tests/processor/community/__init__.py
tests/processor/community/test_markdown_processor.py
tests/processor/docx/__init__.py
tests/processor/docx/test_docx.py
tests/processor/epub/__init__.py
