Metadata-Version: 2.4
Name: quivr-modified-milvus
Version: 0.1.1
Summary: quivr and milvus
Home-page: https://github.com/frechi9/quivr_milvus.git
Author: feng ziyang
Author-email: 2462104908@qq.com
License: MIT
Keywords: sample setuptools development
Requires-Dist: aiofiles==24.1.0
Requires-Dist: aiohappyeyeballs==2.4.3
Requires-Dist: aiohttp==3.10.10
Requires-Dist: aiosignal==1.3.1
Requires-Dist: annotated-types==0.7.0
Requires-Dist: anthropic==0.36.1
Requires-Dist: anyio==4.6.2.post1
Requires-Dist: appnope==0.1.4
Requires-Dist: asttokens==2.4.1
Requires-Dist: attrs==24.2.0
Requires-Dist: black==24.10.0
Requires-Dist: certifi==2024.8.30
Requires-Dist: cfgv==3.4.0
Requires-Dist: charset-normalizer==3.4.0
Requires-Dist: click==8.1.7
Requires-Dist: cohere==5.11.1
Requires-Dist: comm==0.2.2
Requires-Dist: dataclasses-json==0.6.7
Requires-Dist: debugpy==1.8.7
Requires-Dist: decorator==5.1.1
Requires-Dist: defusedxml==0.7.1
Requires-Dist: distlib==0.3.9
Requires-Dist: distro==1.9.0
Requires-Dist: execnet==2.1.1
Requires-Dist: executing==2.1.0
Requires-Dist: faiss-cpu==1.9.0
Requires-Dist: fastavro==1.9.7
Requires-Dist: filelock==3.16.1
Requires-Dist: flake8==7.1.1
Requires-Dist: flake8-black==0.3.6
Requires-Dist: frozenlist==1.4.1
Requires-Dist: fsspec==2024.9.0
Requires-Dist: h11==0.14.0
Requires-Dist: httpcore==1.0.6
Requires-Dist: httpx==0.27.2
Requires-Dist: httpx-sse==0.4.0
Requires-Dist: huggingface-hub==0.25.2
Requires-Dist: identify==2.6.1
Requires-Dist: idna==3.10
Requires-Dist: iniconfig==2.0.0
Requires-Dist: ipykernel==6.29.5
Requires-Dist: ipython==8.28.0
Requires-Dist: jedi==0.19.1
Requires-Dist: jiter==0.6.1
Requires-Dist: jsonpatch==1.33
Requires-Dist: jsonpointer==3.0.0
Requires-Dist: jupyter-client==8.6.3
Requires-Dist: jupyter-core==5.7.2
Requires-Dist: langchain==0.2.16
Requires-Dist: langchain-anthropic==0.1.23
Requires-Dist: langchain-cohere==0.2.4
Requires-Dist: langchain-community==0.2.17
Requires-Dist: langchain-core==0.2.41
Requires-Dist: langchain-experimental==0.0.65
Requires-Dist: langchain-openai==0.1.25
Requires-Dist: langchain-text-splitters==0.2.4
Requires-Dist: langgraph==0.2.38
Requires-Dist: langgraph-checkpoint==2.0.1
Requires-Dist: langgraph-sdk==0.1.33
Requires-Dist: langsmith==0.1.135
Requires-Dist: markdown-it-py==3.0.0
Requires-Dist: marshmallow==3.22.0
Requires-Dist: matplotlib-inline==0.1.7
Requires-Dist: mccabe==0.7.0
Requires-Dist: mdurl==0.1.2
Requires-Dist: msgpack==1.1.0
Requires-Dist: multidict==6.1.0
Requires-Dist: mypy==1.12.0
Requires-Dist: mypy-extensions==1.0.0
Requires-Dist: nest-asyncio==1.6.0
Requires-Dist: nodeenv==1.9.1
Requires-Dist: numpy==1.26.4
Requires-Dist: openai==1.52.0
Requires-Dist: orjson==3.10.7
Requires-Dist: packaging==24.1
Requires-Dist: pandas==2.2.3
Requires-Dist: parameterized==0.9.0
Requires-Dist: parso==0.8.4
Requires-Dist: pathspec==0.12.1
Requires-Dist: pexpect==4.9.0
Requires-Dist: platformdirs==4.3.6
Requires-Dist: pluggy==1.5.0
Requires-Dist: pre-commit==4.0.1
Requires-Dist: prompt-toolkit==3.0.48
Requires-Dist: propcache==0.2.0
Requires-Dist: protobuf==5.28.2
Requires-Dist: psutil==6.0.0
Requires-Dist: ptyprocess==0.7.0
Requires-Dist: pure-eval==0.2.3
Requires-Dist: py-cpuinfo==9.0.0
Requires-Dist: pycodestyle==2.12.1
Requires-Dist: pydantic==2.9.2
Requires-Dist: pydantic-core==2.23.4
Requires-Dist: pyflakes==3.2.0
Requires-Dist: pygments==2.18.0
Requires-Dist: pytest==8.3.3
Requires-Dist: pytest-asyncio==0.24.0
Requires-Dist: pytest-benchmark==4.0.0
Requires-Dist: pytest-xdist==3.6.1
Requires-Dist: python-dateutil==2.8.2
Requires-Dist: pytz==2024.2
Requires-Dist: pyyaml==6.0.2
Requires-Dist: pyzmq==26.2.0
Requires-Dist: rapidfuzz==3.10.1
Requires-Dist: regex==2024.9.11
Requires-Dist: requests==2.32.3
Requires-Dist: requests-toolbelt==1.0.0
Requires-Dist: rich==13.9.2
Requires-Dist: ruff==0.6.9
Requires-Dist: safetensors==0.4.5
Requires-Dist: sentencepiece==0.2.0
Requires-Dist: six==1.16.0
Requires-Dist: sniffio==1.3.1
Requires-Dist: sqlalchemy==2.0.36
Requires-Dist: stack-data==0.6.3
Requires-Dist: tabulate==0.9.0
Requires-Dist: tenacity==8.5.0
Requires-Dist: tiktoken==0.8.0
Requires-Dist: tokenizers==0.20.1
Requires-Dist: tornado==6.4.1
Requires-Dist: tqdm==4.66.5
Requires-Dist: traitlets==5.14.3
Requires-Dist: transformers==4.45.2
Requires-Dist: types-pyyaml==6.0.12.20240917
Requires-Dist: types-requests==2.32.0.20241016
Requires-Dist: typing-extensions==4.12.2
Requires-Dist: typing-inspect==0.9.0
Requires-Dist: tzdata==2024.2
Requires-Dist: urllib3==2.2.3
Requires-Dist: virtualenv==20.26.6
Requires-Dist: wcwidth==0.2.13
Requires-Dist: yarl==1.15.3
Dynamic: author
Dynamic: author-email
Dynamic: home-page
Dynamic: keywords
Dynamic: license
Dynamic: requires-dist
Dynamic: summary
